sphinxcontrib_getstart_sphinx-1.2.0-py3.10-nspkg.pth
sphinxcontrib/getstart_sphinx/__init__.py
sphinxcontrib/getstart_sphinx/better_docref.py
sphinxcontrib/getstart_sphinx/column.py
sphinxcontrib/getstart_sphinx/footnote_relocator.py
sphinxcontrib/getstart_sphinx/glossary_decorator.py
sphinxcontrib/getstart_sphinx/oreilly_review_table.py
sphinxcontrib_getstart_sphinx-1.2.0.dist-info/METADATA
sphinxcontrib_getstart_sphinx-1.2.0.dist-info/WHEEL
sphinxcontrib_getstart_sphinx-1.2.0.dist-info/namespace_packages.txt
sphinxcontrib_getstart_sphinx-1.2.0.dist-info/top_level.txt
sphinxcontrib_getstart_sphinx-1.2.0.dist-info/RECORD
