Metadata-Version: 2.1
Name: sphinxcontrib-getstart-sphinx
Version: 1.2.0
Summary: Sphinx extensions for "Getting Started with Sphinx 2nd Edition"
Home-page: https://github.com/getstart-sphinx/sphinxcontrib-getstart-sphinx
Author: Takeshi KOMIYA
Author-email: i.tkomiya@gmail.com
License: BSD
Platform: any
Classifier: Development Status :: 4 - Beta
Classifier: Environment :: Console
Classifier: Framework :: Sphinx :: Extension
Classifier: Intended Audience :: Developers
Classifier: License :: OSI Approved :: BSD License
Classifier: Operating System :: OS Independent
Classifier: Programming Language :: Python
Classifier: Programming Language :: Python :: 3
Classifier: Programming Language :: Python :: 3.6
Classifier: Topic :: Documentation
Classifier: Topic :: Documentation :: Sphinx
Requires-Dist: Sphinx >=2.0
Requires-Dist: sphinxcontrib-reviewbuilder >=0.0.8
